LICENSE
pieces/__init__.py
pieces/__main__.py
pieces/_vendor/__init__.py
pieces/_vendor/pieces_os_client/__init__.py
pieces/_vendor/pieces_os_client/api/__init__.py
pieces/_vendor/pieces_os_client/api/activities_api.py
pieces/_vendor/pieces_os_client/api/activity_api.py
pieces/_vendor/pieces_os_client/api/allocation_api.py
pieces/_vendor/pieces_os_client/api/allocations_api.py
pieces/_vendor/pieces_os_client/api/analyses_api.py
pieces/_vendor/pieces_os_client/api/anchor_api.py
pieces/_vendor/pieces_os_client/api/anchor_point_api.py
pieces/_vendor/pieces_os_client/api/anchor_points_api.py
pieces/_vendor/pieces_os_client/api/anchors_api.py
pieces/_vendor/pieces_os_client/api/annotation_api.py
pieces/_vendor/pieces_os_client/api/annotations_api.py
pieces/_vendor/pieces_os_client/api/applet_api.py
pieces/_vendor/pieces_os_client/api/application_api.py
pieces/_vendor/pieces_os_client/api/applications_api.py
pieces/_vendor/pieces_os_client/api/asset_api.py
pieces/_vendor/pieces_os_client/api/assets_api.py
pieces/_vendor/pieces_os_client/api/auth0_api.py
pieces/_vendor/pieces_os_client/api/backup_api.py
pieces/_vendor/pieces_os_client/api/backups_api.py
pieces/_vendor/pieces_os_client/api/classification_api.py
pieces/_vendor/pieces_os_client/api/code_analyses_api.py
pieces/_vendor/pieces_os_client/api/connector_api.py
pieces/_vendor/pieces_os_client/api/conversation_api.py
pieces/_vendor/pieces_os_client/api/conversation_message_api.py
pieces/_vendor/pieces_os_client/api/conversation_messages_api.py
pieces/_vendor/pieces_os_client/api/conversations_api.py
pieces/_vendor/pieces_os_client/api/database_api.py
pieces/_vendor/pieces_os_client/api/discovery_api.py
pieces/_vendor/pieces_os_client/api/distribution_api.py
pieces/_vendor/pieces_os_client/api/distributions_api.py
pieces/_vendor/pieces_os_client/api/external_provider_api.py
pieces/_vendor/pieces_os_client/api/format_api.py
pieces/_vendor/pieces_os_client/api/formats_api.py
pieces_cli-1.19.0.dist-info/METADATA
pieces_cli-1.19.0.dist-info/WHEEL
pieces_cli-1.19.0.dist-info/entry_points.txt
pieces_cli-1.19.0.dist-info/licenses/LICENSE
pieces_cli-1.19.0.dist-info/RECORD
