Metadata-Version: 2.4
Name: pieces-cli
Version: 1.19.0
Summary: A powerful cli tool to interact with PiecesOS 
License: MIT
License-File: LICENSE
Keywords: copilot,pieces,ai,snippets,materials
Author: Pieces
Author-email: development@pieces.app
Requires-Python: >=3.11,<3.15
Classifier: License :: OSI Approved :: MIT License
Classifier: Programming Language :: Python :: 3
Classifier: Programming Language :: Python :: 3.11
Classifier: Programming Language :: Python :: 3.12
Classifier: Programming Language :: Python :: 3.13
Classifier: Programming Language :: Python :: 3.14
Provides-Extra: tui
Requires-Dist: aenum (>=3.1.11)
Requires-Dist: mcp (==1.17.0)
Requires-Dist: platformdirs (>=4.2.0,<5.0.0)
Requires-Dist: prompt-toolkit (>=3.0.43,<4.0.0)
Requires-Dist: pydantic (==2.12.0)
Requires-Dist: pyperclip (>=1.8.2)
Requires-Dist: python-dateutil (>=2.8.2)
Requires-Dist: pyyaml (>=6.0.2,<7.0.0)
Requires-Dist: rich (>=14.2.0,<15.0.0)
Requires-Dist: sentry-sdk (>=2.34.1,<3.0.0)
Requires-Dist: textual[syntax] (>=5.3.0,<6.0.0) ; extra == "tui"
Requires-Dist: urllib3 (>=2.5.0)
Requires-Dist: websocket-client (>=1.8.0,<2.0.0)
Project-URL: Homepage, https://pieces.app
Project-URL: Repository, https://github.com/pieces-app/cli-agent
